larus/__init__.py
larus/arbiter.py
larus/utils.py
larus/wsgi.py
larus/scripts/__init__.py
larus/scripts/manage.py
larus/workers/__init__.py
larus/workers/base.py
larus/workers/sync.py
larus-0.3.1.dist-info/DESCRIPTION.rst
larus-0.3.1.dist-info/entry_points.txt
larus-0.3.1.dist-info/METADATA
larus-0.3.1.dist-info/metadata.json
larus-0.3.1.dist-info/RECORD
larus-0.3.1.dist-info/top_level.txt
larus-0.3.1.dist-info/WHEEL
