Metadata-Version: 2.0
Name: larus
Version: 0.3.1
Summary: Larus is a simplified Gunicorn clone
Home-page: https://github.com/wong2/larus
Author: wong2
Author-email: wonderfuly@gmail.com
License: BSD
Keywords: larus,gunicorn,wsgi
Platform: UNKNOWN
Classifier: Development Status :: 2 - Pre-Alpha
Classifier: Intended Audience :: Developers
Classifier: License :: OSI Approved :: BSD License
Classifier: Natural Language :: English
Classifier: Programming Language :: Python :: 2.6
Classifier: Programming Language :: Python :: 2.7
Requires-Dist: http-parser
Requires-Dist: click
